COPYING
COPYING.LESSER
INSTALL.rst
MANIFEST.in
README.rst
setup.cfg
setup.py
common_context/__init__.py
common_context/context_processors/__init__.py
django_common_context.egg-info/PKG-INFO
django_common_context.egg-info/SOURCES.txt
django_common_context.egg-info/dependency_links.txt
django_common_context.egg-info/not-zip-safe
django_common_context.egg-info/requires.txt
django_common_context.egg-info/top_level.txt